Metadata-Version: 1.1
Name: pyplugins
Version: 1.3
Summary: A plugin system to extends features into your application
Home-page: https://github.com/di3g0bs0n/pyplugins
Author: Diego Fernandez
Author-email: di3g0bs0n@gmail.com
License: GPLv3
Keywords: python sdk plugins extends
Platform: UNKNOWN
Classifier: Development Status :: 5 - Production/Stable
Classifier: License :: OSI Approved :: GNU General Public License v3 (GPLv3)
Classifier: Programming Language :: Python :: 3.6
Classifier: Topic :: Utilities
